IEXWrapper/__init__.py
IEXWrapper/classes.py
IEXWrapper/config.py
IEXWrapper/wrapper_base.py
IEXWrapper/exceptions/__init__.py
IEXWrapper-1.0.5.dist-info/LICENSE
IEXWrapper-1.0.5.dist-info/METADATA
IEXWrapper-1.0.5.dist-info/WHEEL
IEXWrapper-1.0.5.dist-info/top_level.txt
IEXWrapper-1.0.5.dist-info/zip-safe
IEXWrapper-1.0.5.dist-info/RECORD
