Metadata-Version: 2.1
Name: IEXWrapper
Version: 1.0.5
Summary: A simple py wrapper to IEX Trading API
Home-page: https://github.com/Usernameles/IEXWrapper
Author: Adriano Gigliuto
Author-email: 8vd2roma@gmail.com
License: GNU
Platform: UNKNOWN
